[{"market":"電子紙","vmn":3.96,"vmx":6.24,"tov":2.16,"k":1,"cc":2,"dls":"振曜,元太"},{"market":"AI智慧設備","vmn":3.86,"vmx":5.0,"tov":6.65,"k":1,"cc":2,"dls":"由田,華電網"},{"market":"IC設計","vmn":3.54,"vmx":6.38,"tov":3.94,"k":1,"cc":3,"dls":"矽統,聯發科,威盛"},{"market":"休閒車業","vmn":3.47,"vmx":3.47,"tov":0.64,"k":0,"cc":1,"dls":"美利達"},{"market":"電動車","vmn":3.37,"vmx":3.37,"tov":2.88,"k":1,"cc":1,"dls":"貿聯-KY"},{"market":"先進封裝","vmn":3.03,"vmx":3.03,"tov":1.48,"k":1,"cc":1,"dls":"豪勉"},{"market":"五金元件","vmn":2.94,"vmx":2.94,"tov":4.99,"k":1,"cc":1,"dls":"中砂"},{"market":"醫療器材","vmn":2.72,"vmx":2.72,"tov":1.28,"k":0,"cc":1,"dls":"熒茂"},{"market":"觸控面板","vmn":2.7,"vmx":4.67,"tov":1.46,"k":1,"cc":2,"dls":"精金,TPK-KY"},{"market":"LED磊晶","vmn":2.64,"vmx":5.5,"tov":3.38,"k":1,"cc":5,"dls":"光鋐,泰谷,富采,台亞,同欣電"},{"market":"砷化鎵","vmn":2.43,"vmx":4.18,"tov":1.59,"k":1,"cc":3,"dls":"全新,宏捷科,穩懋"},{"market":"汽車保險桿","vmn":2.35,"vmx":2.35,"tov":0.61,"k":1,"cc":1,"dls":"神達"},{"market":"海陸空貨運承攬","vmn":2.32,"vmx":4.22,"tov":0.32,"k":1,"cc":3,"dls":"台灣高鐵,長榮航太,華航"},{"market":"電池模組","vmn":2.31,"vmx":4.33,"tov":1.83,"k":1,"cc":3,"dls":"順達,美律,新普"},{"market":"PC機殼","vmn":2.3,"vmx":3.85,"tov":8.38,"k":1,"cc":5,"dls":"柏騰,可成,迎廣,能率,晟銘電"},{"market":"汽車保險桿","vmn":2.21,"vmx":2.21,"tov":0.97,"k":0,"cc":1,"dls":"艾姆勒"},{"market":"通信網路","vmn":2.12,"vmx":4.37,"tov":6.1,"k":1,"cc":8,"dls":"正文,正基,智邦,訊舟,星通,友訊,中磊,凱碩"},{"market":"連接器","vmn":1.94,"vmx":3.14,"tov":3.82,"k":1,"cc":7,"dls":"湧德,佳必琪,信音,泰碩,金橋,建舜電,嘉澤"},{"market":"平面顯示器","vmn":1.91,"vmx":3.16,"tov":0.94,"k":1,"cc":3,"dls":"彩晶,凌巨,錸寶"},{"market":"AI機器人","vmn":1.91,"vmx":4.54,"tov":14.75,"k":1,"cc":19,"dls":"系統電,廣明,所羅門,陽程,均豪,盟立,聰泰,志聖,彬台,廣運,昆盈,聯策,慶騰,和椿,慧友,穎漢,金寶,羅昇,高鋒"},{"market":"IC導線架","vmn":1.9,"vmx":2.83,"tov":2.7,"k":1,"cc":4,"dls":"順德,健策,一詮,長科*"},{"market":"AI運算設備","vmn":1.9,"vmx":2.4,"tov":0.74,"k":1,"cc":2,"dls":"明泰,緯穎"},{"market":"低軌衛星","vmn":1.89,"vmx":3.56,"tov":3.71,"k":1,"cc":3,"dls":"建漢,仲琦,啟碁"},{"market":"IC面板驅動","vmn":1.89,"vmx":1.89,"tov":0.51,"k":1,"cc":1,"dls":"聯詠"},{"market":"餐飲連鎖","vmn":1.88,"vmx":1.88,"tov":5.26,"k":1,"cc":1,"dls":"御頂"},{"market":"食品","vmn":1.88,"vmx":1.98,"tov":0.17,"k":0,"cc":2,"dls":"大成,愛之味"},{"market":"金融","vmn":1.87,"vmx":4.07,"tov":0.36,"k":0,"cc":4,"dls":"遠東銀,美好證,國票金,三商壽"},{"market":"紡織","vmn":1.84,"vmx":6.13,"tov":1.56,"k":1,"cc":10,"dls":"廣豐,台富,佳和,力鵬,力麗,南紡,大將,如興,聚陽,福大"},{"market":"美超微MCSI","vmn":1.82,"vmx":1.82,"tov":0.62,"k":1,"cc":1,"dls":"華泰"},{"market":"橡膠製品","vmn":1.81,"vmx":3.43,"tov":0.16,"k":1,"cc":4,"dls":"南帝,厚生,國際中橡,台橡"},{"market":"汽電共生","vmn":1.77,"vmx":1.77,"tov":0.18,"k":1,"cc":1,"dls":"台汽電"},{"market":"區塊鏈","vmn":1.75,"vmx":1.75,"tov":0.95,"k":0,"cc":1,"dls":"映泰"},{"market":"PC安全監控系統","vmn":1.74,"vmx":1.74,"tov":1.43,"k":1,"cc":1,"dls":"奇偶"},{"market":"光通訊設備","vmn":1.71,"vmx":2.42,"tov":3.58,"k":1,"cc":6,"dls":"聯光通,華星光,波若威,眾達-KY,上詮,盛達"},{"market":"IP","vmn":1.7,"vmx":2.54,"tov":2.71,"k":1,"cc":4,"dls":"世芯-KY,創意,M31,智原"},{"market":"FOPLP封裝","vmn":1.65,"vmx":2.07,"tov":31.72,"k":1,"cc":2,"dls":"晶彩科,友威科"},{"market":"連接器","vmn":1.64,"vmx":2.1,"tov":4.18,"k":0,"cc":2,"dls":"優群,瀚荃"},{"market":"LED封裝模組","vmn":1.64,"vmx":2.53,"tov":2.82,"k":1,"cc":7,"dls":"雷科,聯嘉,中釉,光寶科,達興材料,榮創,華興"},{"market":"金屬加工用機械","vmn":1.63,"vmx":3.43,"tov":7.02,"k":1,"cc":5,"dls":"瀧澤科,高力,元翎,百德,健椿"},{"market":"神盾集團","vmn":1.63,"vmx":1.73,"tov":8.79,"k":1,"cc":3,"dls":"神盾,安格,安國"},{"market":"油電燃氣","vmn":1.61,"vmx":1.61,"tov":0.08,"k":0,"cc":1,"dls":"台塑化"},{"market":"線上遊戲","vmn":1.6,"vmx":2.77,"tov":0.6,"k":1,"cc":3,"dls":"大宇資,鈊象,橘子"},{"market":"通信被動元件","vmn":1.57,"vmx":1.7,"tov":0.66,"k":1,"cc":2,"dls":"聯亞,連展投控"},{"market":"PC","vmn":1.57,"vmx":2.1,"tov":0.72,"k":1,"cc":7,"dls":"振發,致伸,群光,銘異,輔信,虹堡,事欣科"},{"market":"重電","vmn":1.55,"vmx":1.55,"tov":0.28,"k":0,"cc":1,"dls":"東元"},{"market":"AI機器學習","vmn":1.54,"vmx":1.68,"tov":1.54,"k":1,"cc":2,"dls":"芯鼎,零壹"},{"market":"汽車零組件AM","vmn":1.51,"vmx":1.51,"tov":0.39,"k":1,"cc":1,"dls":"東陽"},{"market":"PCB","vmn":1.51,"vmx":4.52,"tov":1.24,"k":1,"cc":28,"dls":"華通,金像電,同泰,楠梓電,高技,台虹,泰鼎-KY,敬鵬,聯茂,嘉聯益,富喬,台燿,欣興,台光電,長興,凱崴,毅嘉,健鼎,恩德,南電,晟鈦,德宏,精成科,合正,廣宇,臻鼎-KY,瀚宇博,達邁"}]